drb/drivers/zarr/__init__.py
drb/drivers/zarr/_version.py
drb/drivers/zarr/zarr_data_set_node.py
drb/drivers/zarr/zarr_node_factory.py
drb/exceptions/zarr.py
drb/topics/zarr/__init__.py
drb/topics/zarr/cortex.yml
drb_driver_zarr-1.3.0.dist-info/LICENCE.txt
drb_driver_zarr-1.3.0.dist-info/METADATA
drb_driver_zarr-1.3.0.dist-info/WHEEL
drb_driver_zarr-1.3.0.dist-info/entry_points.txt
drb_driver_zarr-1.3.0.dist-info/top_level.txt
drb_driver_zarr-1.3.0.dist-info/RECORD
